{
  "d99f7950-2254-44ad-8ec9-1fdb9ed661c5": {
    "preferences": {
      "apricot": 4.0,
      "sugar": 4.0,
      "of kosher salt": 4.0,
      "split lengthwise": 3.0,
      "peach": 3.0,
      "jam plum": 3.0,
      "unsweetened almond milk": 3.0,
      "vanilla bean": 3.0,
      "short-grain brown rice": 3.0,
      "blanched hazelnuts": 3.0,
      "salsa": 1.9,
      "kosa": 1.9,
      "gazar": 1.9
    },
    "meal_type_preferences": {
      "breakfast": 2,
      "lunch": 2
    },
    "cooking_time_preferences": {
      "medium": 2,
      "long": 2
    },
    "ingredient_combinations": {
      "apricot+sugar": 1,
      "apricot+of kosher salt": 1,
      "sugar+of kosher salt": 1,
      "sugar+split lengthwise": 1,
      "of kosher salt+split lengthwise": 1,
      "of kosher salt+peach": 1,
      "split lengthwise+peach": 1,
      "split lengthwise+jam plum": 1,
      "peach+jam plum": 1,
      "peach+unsweetened almond milk": 1,
      "jam plum+unsweetened almond milk": 1,
      "jam plum+vanilla bean": 1,
      "unsweetened almond milk+vanilla bean": 1,
      "unsweetened almond milk+short-grain brown rice": 1,
      "vanilla bean+short-grain brown rice": 1,
      "vanilla bean+blanched hazelnuts": 1,
      "short-grain brown rice+blanched hazelnuts": 1,
      "salsa+kosa": 1,
      "salsa+gazar": 1,
      "kosa+gazar": 1
    },
    "updated_at": "2025-06-26T20:09:51.127477",
    "cooking_history": [
      {
        "recipe_name": "Brown Rice Porridge with Hazelnuts and Jam",
        "ingredients": [
          "apricot",
          "sugar",
          "of kosher salt",
          "split lengthwise",
          "peach",
          "jam plum",
          "unsweetened almond milk",
          "vanilla bean",
          "short-grain brown rice",
          "blanched hazelnuts"
        ],
        "meal_type": "Breakfast",
        "cooking_time": "Under 30 mins",
        "cooked_at": "2025-06-23T20:08:43.483482",
        "preference_boosts": {
          "apricot": 4.0,
          "sugar": 4.0,
          "of kosher salt": 4.0,
          "split lengthwise": 3.0,
          "peach": 3.0,
          "jam plum": 3.0,
          "unsweetened almond milk": 3.0,
          "vanilla bean": 3.0,
          "short-grain brown rice": 3.0,
          "blanched hazelnuts": 3.0
        }
      },
      {
        "recipe_name": "5altabeta bel salsa",
        "ingredients": [
          "salsa",
          "kosa",
          "gazar"
        ],
        "meal_type": "Lunch",
        "cooking_time": "30-60 mins",
        "cooked_at": "2025-06-26T20:09:51.127477",
        "preference_boosts": {
          "salsa": 1.9,
          "kosa": 1.9,
          "gazar": 1.9
        }
      }
    ]
  }
}